setup.py
tradein.py
aws_trade_in.egg-info/PKG-INFO
aws_trade_in.egg-info/SOURCES.txt
aws_trade_in.egg-info/dependency_links.txt
aws_trade_in.egg-info/requires.txt
aws_trade_in.egg-info/top_level.txt
bin/aws-trade-in