Metadata-Version: 1.0
Name: aws-trade-in
Version: 0.1
Summary: Amazon Trade-In Helper
Home-page: http://github.com/dlecocq/aws-trade-in
Author: Dan Lecocq
Author-email: dan@seomoz.org
License: UNKNOWN
Platform: Posix; MacOS X
Classifier: Development Status :: 3 - Alpha
Classifier: Environment :: Console
Classifier: Intended Audience :: Developers
Classifier: Topic :: System :: Shells
